{
  "date": "2026-04-19",
  "url": "http://localhost:3001",
  "healthScore": 95,
  "issues": [
    {
      "id": "ISSUE-001",
      "title": "Dashboard shows low-severity hydration warning in dev",
      "severity": "low",
      "category": "console"
    },
    {
      "id": "ISSUE-002",
      "title": "Budget tab switching has minor perceived delay",
      "severity": "low",
      "category": "ux"
    }
  ],
  "categoryScores": {
    "console": 95,
    "links": 100,
    "visual": 97,
    "functional": 98,
    "ux": 90,
    "performance": 90,
    "content": 98,
    "accessibility": 95
  }
}
